pdfa_learning/__init__.py
pdfa_learning/helpers/__init__.py
pdfa_learning/helpers/base.py
pdfa_learning/learn_pdfa/__init__.py
pdfa_learning/learn_pdfa/balle/__init__.py
pdfa_learning/learn_pdfa/balle/core.py
pdfa_learning/learn_pdfa/balle/params.py
pdfa_learning/learn_pdfa/base.py
pdfa_learning/learn_pdfa/palmer/__init__.py
pdfa_learning/learn_pdfa/palmer/core.py
pdfa_learning/learn_pdfa/palmer/learn_probabilities.py
pdfa_learning/learn_pdfa/palmer/learn_subgraph.py
pdfa_learning/learn_pdfa/palmer/params.py
pdfa_learning/learn_pdfa/utils/__init__.py
pdfa_learning/learn_pdfa/utils/base.py
pdfa_learning/learn_pdfa/utils/generator.py
pdfa_learning/learn_pdfa/utils/multiset/__init__.py
pdfa_learning/learn_pdfa/utils/multiset/base.py
pdfa_learning/learn_pdfa/utils/multiset/naive.py
pdfa_learning/learn_pdfa/utils/multiset/tree.py
pdfa_learning/pdfa/__init__.py
pdfa_learning/pdfa/base.py
pdfa_learning/pdfa/helpers.py
pdfa_learning/pdfa/render.py
pdfa_learning/types.py
pdfa_learning-0.1.0.dist-info/LICENSE
pdfa_learning-0.1.0.dist-info/WHEEL
pdfa_learning-0.1.0.dist-info/METADATA
pdfa_learning-0.1.0.dist-info/RECORD
